[
  {"type": "salary_to_hourly", "salary": 20000},
  {"type": "salary_to_hourly", "salary": 25000},
  {"type": "salary_to_hourly", "salary": 30000},
  {"type": "salary_to_hourly", "salary": 35000},
  {"type": "salary_to_hourly", "salary": 40000},
  {"type": "salary_to_hourly", "salary": 45000},
  {"type": "salary_to_hourly", "salary": 50000},
  {"type": "salary_to_hourly", "salary": 55000},
  {"type": "salary_to_hourly", "salary": 60000},
  {"type": "salary_to_hourly", "salary": 65000},
  {"type": "salary_to_hourly", "salary": 70000},
  {"type": "salary_to_hourly", "salary": 75000},
  {"type": "salary_to_hourly", "salary": 80000},
  {"type": "salary_to_hourly", "salary": 85000},
  {"type": "salary_to_hourly", "salary": 90000},
  {"type": "salary_to_hourly", "salary": 95000},
  {"type": "salary_to_hourly", "salary": 100000},
  {"type": "salary_to_hourly", "salary": 110000},
  {"type": "salary_to_hourly", "salary": 120000},
  {"type": "salary_to_hourly", "salary": 130000},
  {"type": "salary_to_hourly", "salary": 140000},
  {"type": "salary_to_hourly", "salary": 150000},
  {"type": "salary_to_hourly", "salary": 175000},
  {"type": "salary_to_hourly", "salary": 200000},
  {"type": "salary_to_hourly", "salary": 250000},
  {"type": "hourly_to_salary", "hourly": 7.25},
  {"type": "hourly_to_salary", "hourly": 8},
  {"type": "hourly_to_salary", "hourly": 9},
  {"type": "hourly_to_salary", "hourly": 10},
  {"type": "hourly_to_salary", "hourly": 11},
  {"type": "hourly_to_salary", "hourly": 12},
  {"type": "hourly_to_salary", "hourly": 13},
  {"type": "hourly_to_salary", "hourly": 14},
  {"type": "hourly_to_salary", "hourly": 15},
  {"type": "hourly_to_salary", "hourly": 16},
  {"type": "hourly_to_salary", "hourly": 17},
  {"type": "hourly_to_salary", "hourly": 18},
  {"type": "hourly_to_salary", "hourly": 19},
  {"type": "hourly_to_salary", "hourly": 20},
  {"type": "hourly_to_salary", "hourly": 21},
  {"type": "hourly_to_salary", "hourly": 22},
  {"type": "hourly_to_salary", "hourly": 23},
  {"type": "hourly_to_salary", "hourly": 24},
  {"type": "hourly_to_salary", "hourly": 25},
  {"type": "hourly_to_salary", "hourly": 26},
  {"type": "hourly_to_salary", "hourly": 27},
  {"type": "hourly_to_salary", "hourly": 28},
  {"type": "hourly_to_salary", "hourly": 29},
  {"type": "hourly_to_salary", "hourly": 30},
  {"type": "hourly_to_salary", "hourly": 32},
  {"type": "hourly_to_salary", "hourly": 35},
  {"type": "hourly_to_salary", "hourly": 37},
  {"type": "hourly_to_salary", "hourly": 40},
  {"type": "hourly_to_salary", "hourly": 42},
  {"type": "hourly_to_salary", "hourly": 45},
  {"type": "hourly_to_salary", "hourly": 47},
  {"type": "hourly_to_salary", "hourly": 50},
  {"type": "hourly_to_salary", "hourly": 55},
  {"type": "hourly_to_salary", "hourly": 60},
  {"type": "hourly_to_salary", "hourly": 65},
  {"type": "hourly_to_salary", "hourly": 70},
  {"type": "hourly_to_salary", "hourly": 75},
  {"type": "hourly_to_salary", "hourly": 80},
  {"type": "hourly_to_salary", "hourly": 85},
  {"type": "hourly_to_salary", "hourly": 90},
  {"type": "hourly_to_salary", "hourly": 95},
  {"type": "hourly_to_salary", "hourly": 100}
]
